ftp2http-0.3.6.dist-info/METADATA
ftp2http-0.3.6.dist-info/RECORD
ftp2http-0.3.6.dist-info/top_level.txt
ftp2http-0.3.6.dist-info/entry_points.txt
ftp2http-0.3.6.dist-info/WHEEL
ftp2http-0.3.6.dist-info/zip-safe
ftp2http-0.3.6.dist-info/DESCRIPTION.rst
ftp2http-0.3.6.dist-info/metadata.json
ftp2http/version.py
ftp2http/ftp2http.py
ftp2http/__init__.py
ftp2http/__main__.py
