Metadata-Version: 2.0
Name: ftp2http
Version: 0.3.6
Summary: FTP to HTTP server
Home-page: https://github.com/apnarm/ftp2http
Author: APN Online
Author-email: dev.admin@apnonline.com.au
License: MIT
Platform: UNKNOWN
Requires-Dist: argparse
Requires-Dist: pyftpdlib
Requires-Dist: pyOpenSSL
Requires-Dist: py-bcrypt
Requires-Dist: python-swiftclient (==1.9.0)
